[
  {
    "timesSeen" : [
      1741720313.6,
      1747784845.3,
      1747872239.7,
      1748577098.3,
      1749439715.2,
      1753979503.5,
      1754782327.7,
      1754970127,
      1755298088.8,
      1755733399,
      1755820020.8,
      1755833516.1000001
    ],
    "flights" : {
      "TAP211  " : 1,
      "TAP201  " : 1,
      "TAP228  " : 1
    },
    "properties" : {
      "registered_owner_country_name" : "Portugal",
      "manufacturer" : "Airbus",
      "registration" : "CS-TXF",
      "registered_owner" : "TAP Air Portugal",
      "registered_owner_country_iso_name" : "PT",
      "registered_owner_operator_flag_code" : "TAP",
      "icao_type" : "A21N",
      "type" : "A321 251NXSL"
    },
    "lastSeen" : 1755834547,
    "hex" : "495306"
  },
  {
    "timesSeen" : [
      1741036424.5,
      1741713500.2,
      1741723592.6000001,
      1741815162.6,
      1741820295.2,
      1741867599.1999998,
      1741901749.1,
      1741905379.5,
      1741982643.3,
      1742003968.8999999,
      1742077789.3,
      1742081526.6,
      1742332423.3999999,
      1742347321.7,
      1742665434.3999999,
      1742687602.4,
      1743078557.2,
      1748966101.1,
      1749080075.2,
      1749089387.8999999,
      1751230558.1,
      1751251463.7,
      1751410823.6,
      1751422627.1,
      1751495187.5,
      1751509000.3999999,
      1751644763.3999999,
      1751668551.1,
      1751749138,
      1751753469.5,
      1751843242.2,
      1753314408.8,
      1753459402.3,
      1753483967.8,
      1753495972.3,
      1753566067,
      1753569687.1999998,
      1753747169.9,
      1753806201.3,
      1753809804.5,
      1753818966,
      1753822596.3,
      1753826654.6999998,
      1753831676.6999998,
      1753914290,
      1753918575.5,
      1754065987.5,
      1754341338.6000001,
      1754663806.5,
      1754694261.6,
      1754831452.9,
      1754835236.8,
      1754858430.3,
      1754862058.6,
      1754931291.3,
      1754954058.6000001,
      1755000251.6000001,
      1755003892.5,
      1755011790.3,
      1755024340.1999998,
      1755097383.8,
      1755114862.3,
      1755118472.8999999,
      1755294534.1999998,
      1755357119.3999999,
      1755367220.6,
      1755381386.6,
      1755394029.8,
      1755441775.7,
      1755546836.1,
      1755619408.8,
      1755634275.5,
      1755800780.9,
      1755806377.5,
      1755814987.8,
      1755833576.4
    ],
    "flights" : {
      "N22WX   " : 35
    },
    "lastSeen" : 1755834473.6000001,
    "hex" : "a1e0b2"
  },
  {
    "timesSeen" : [
      1740503971.8999999,
      1740763419.3999999,
      1741882026.8999999,
      1743721210.3,
      1744483207.8,
      1744587710.4,
      1745509838.5,
      1745607394.8,
      1745737631.3000002,
      1746218050.9,
      1746298040.3,
      1746319323.8999999,
      1747947265.5,
      1751299755.6999998,
      1751579564.6000001,
      1753648269,
      1753728677.3,
      1754166240.1,
      1754350800.3999999,
      1755633775.1,
      1755705374.2,
      1755794505.7,
      1755834146.3
    ],
    "flights" : {
      "UAL85   " : 1,
      "UAL995  " : 2,
      "UAL90   " : 1
    },
    "properties" : {
      "registered_owner_country_name" : "United States",
      "manufacturer" : "Boeing",
      "registration" : "N17015",
      "registered_owner" : "United Airlines",
      "registered_owner_country_iso_name" : "US",
      "registered_owner_operator_flag_code" : "UAL",
      "icao_type" : "B78X",
      "type" : "787 10"
    },
    "lastSeen" : 1755834371.3999999,
    "hex" : "a11bc6"
  },
  {
    "timesSeen" : [
      1748559419.1,
      1748830935.5,
      1753477320.1999998,
      1755114986.8,
      1755436362.9,
      1755528816.7,
      1755831929.3
    ],
    "flights" : {
      "N617BW  " : 2
    },
    "properties" : {
      "registered_owner_country_name" : "United States",
      "manufacturer" : "Bombardier",
      "registration" : "N617BW",
      "registered_owner" : "White Aviation Holdings LLC",
      "registered_owner_country_iso_name" : "US",
      "registered_owner_operator_flag_code" : "CL64",
      "icao_type" : "CL64",
      "type" : "Challenger 604"
    },
    "lastSeen" : 1755834369.5,
    "hex" : "a808ed"
  },
  {
    "timesSeen" : [
      1740688351,
      1740693660.2,
      1741792937.7,
      1741799633.5,
      1741977508.6,
      1745170668.9,
      1748702038.7,
      1748708803.9,
      1753589513,
      1753611822.7,
      1753676579.6999998,
      1753694689.7,
      1754077190.2,
      1754083738.5,
      1754711277.3,
      1754736638.9,
      1754763550.7,
      1754818089,
      1755833697
    ],
    "flights" : {
      "EDV5277 " : 1,
      "EDV5295 " : 2,
      "EDV5151 " : 1
    },
    "properties" : {
      "registered_owner_country_name" : "United States",
      "manufacturer" : "Bombardier",
      "registration" : "N924XJ",
      "registered_owner" : "Delta Connection",
      "url_photo" : "https:\/\/airport-data.com\/images\/aircraft\/001\/694\/001694089.jpg",
      "registered_owner_country_iso_name" : "US",
      "registered_owner_operator_flag_code" : "EDV",
      "icao_type" : "CRJ9",
      "type" : "CRJ 900 LR NG"
    },
    "lastSeen" : 1755834367.1,
    "hex" : "accf1c"
  },
  {
    "timesSeen" : [
      1751321909.1,
      1751407101,
      1751422415.3000002,
      1753282015.3,
      1753287440.8999999,
      1753797357.7,
      1753803650.1000001,
      1755833336.8
    ],
    "flights" : {
      "RPA4460 " : 1,
      "RPA4786 " : 1
    },
    "properties" : {
      "registered_owner_country_name" : "United States",
      "manufacturer" : "Embraer",
      "registration" : "N134HQ",
      "registered_owner" : "American Eagle",
      "url_photo" : "https:\/\/airport-data.com\/images\/aircraft\/001\/007\/001007903.jpg",
      "registered_owner_country_iso_name" : "US",
      "registered_owner_operator_flag_code" : "RPA",
      "icao_type" : "E75S",
      "type" : "EMB-175 LR"
    },
    "lastSeen" : 1755834364.4,
    "hex" : "a08acb"
  },
  {
    "timesSeen" : [
      1744155271.3000002,
      1744240810.2,
      1744329657.1,
      1744413036.5,
      1744500949.1,
      1744588749.5,
      1744603095,
      1744757749.6000001,
      1744845773.6000001,
      1744860819.3000002,
      1744933118,
      1745017175.9,
      1745363476,
      1745449965.8000002,
      1745535423.1,
      1745621833.4,
      1745637195.3000002,
      1745710592,
      1745726400.1000001,
      1745797462.9,
      1745813832.8000002,
      1745969125.8,
      1745984690.1,
      1746055672.2,
      1746313901,
      1746401224.5,
      1746573668.5,
      1746589972,
      1747176675,
      1747262273.2,
      1747280523.5,
      1747351295.8,
      1747366973.6,
      1747436454.2,
      1747522636.8000002,
      1747610046.5,
      1747781178.2,
      1747869244.5,
      1747955971,
      1748041676.2,
      1748127257.8,
      1748215121.1000001,
      1748390429.7,
      1748405787.3999999,
      1748476465.3,
      1748563148.7,
      1748647067.6000001,
      1748734546.3,
      1748835049.6000001,
      1748991991.8000002,
      1749006320.9,
      1749079567.5,
      1749267920.3999999,
      1749341409.3,
      1749356057.2,
      1749424389.3,
      1749440033.4,
      1750547616.3999999,
      1751082273.7,
      1751152437.1,
      1751168651.9,
      1751240648.1,
      1751257078.3999999,
      1751412137.1999998,
      1751426678.1000001,
      1751515428.2,
      1751586289.6000001,
      1751603369.8,
      1751674741,
      1751688737.8,
      1751758165.1,
      1751844524.6,
      1753234431.1,
      1753311549.1,
      1753327144.4,
      1753398327.6999998,
      1753413039.6,
      1753663343.5,
      1753677180.8,
      1753831191,
      1753918784.3,
      1753934105.1,
      1754004848.3999999,
      1754020230.8000002,
      1754090003.1,
      1754105453.7,
      1754177296.4,
      1754192702.2,
      1754266401,
      1754280770,
      1754349793.4,
      1754363384.6999998,
      1754435870,
      1754451322.8,
      1754524751.2,
      1754538620.8,
      1754609709.3999999,
      1754625105.7,
      1754695192.8999999,
      1754709644.1,
      1754782363.9,
      1754870228.3999999,
      1754885283,
      1755055225.8999999,
      1755130821.3,
      1755146760.3,
      1755215105.3000002,
      1755230319.6,
      1755299655.3,
      1755314070.5,
      1755385002.7,
      1755401298.2,
      1755473277.5,
      1755488446.7,
      1755653719,
      1755667585.4,
      1755734355.6,
      1755819227.1,
      1755833965.9
    ],
    "flights" : {
      "LOT5N   " : 9,
      "LOT4TL  " : 3
    },
    "lastSeen" : 1755834343.3,
    "hex" : "495278"
  },
  {
    "timesSeen" : [
      1740961344.7,
      1741585089.4,
      1741636266.8000002,
      1741727849.5,
      1743787307.5,
      1744736233.3999999,
      1745006728.5,
      1745265156.2,
      1745341728.7,
      1745431301.5,
      1745511905.8,
      1745879086.6,
      1745941879.9,
      1746572522.3,
      1747711134.6,
      1749441928.8999999,
      1751649779.6000001,
      1753226285.7,
      1753485973.9,
      1753569448.8,
      1753853486.1,
      1753940384.9,
      1754352364.1,
      1754419363.6,
      1754493209.9,
      1754866234,
      1754924684.4,
      1754975805.3,
      1755463045,
      1755484149.6000001,
      1755546961,
      1755834128.3
    ],
    "flights" : {
      "AAL173  " : 1,
      "AAL731  " : 1,
      "AAL717  " : 1,
      "AAL132  " : 1,
      "AAL705  " : 1
    },
    "properties" : {
      "registered_owner_country_name" : "United States",
      "manufacturer" : "Boeing",
      "registration" : "N774AN",
      "registered_owner" : "American Airlines",
      "url_photo" : "https:\/\/airport-data.com\/images\/aircraft\/001\/498\/001498611.jpg",
      "registered_owner_country_iso_name" : "US",
      "registered_owner_operator_flag_code" : "AAL",
      "icao_type" : "B772",
      "type" : "777 223ER"
    },
    "lastSeen" : 1755834311.7,
    "hex" : "aa77f0"
  },
  {
    "timesSeen" : [
      1745880919,
      1745897917.6000001,
      1751394900.6,
      1751409600.8999999,
      1751482062.7,
      1751497932.1000001,
      1751837153.7,
      1751851411.9,
      1753296087.2,
      1753479194.1000001,
      1753494155.8,
      1753576662.5,
      1753665743.5,
      1753749948.9,
      1753815611.1,
      1753829778.5,
      1754004728.2,
      1754021319.4,
      1755120131.8,
      1755219265.8,
      1755283902.1000001,
      1755297546.7,
      1755726172.3999999,
      1755740525.3,
      1755834122.1
    ],
    "flights" : {
      "LOT6JK  " : 1,
      "LOT18   " : 1,
      "LOT16M  " : 1,
      "LOT7    " : 1,
      "LOT1MU  " : 1
    },
    "properties" : {
      "registered_owner_country_name" : "Poland",
      "manufacturer" : "Boeing",
      "registration" : "SP-LRF",
      "registered_owner" : "LOT Polish Airlines",
      "url_photo" : "https:\/\/airport-data.com\/images\/aircraft\/001\/679\/001679616.jpg",
      "registered_owner_country_iso_name" : "PL",
      "registered_owner_operator_flag_code" : "LOT",
      "icao_type" : "B788",
      "type" : "787 8"
    },
    "lastSeen" : 1755834304.7,
    "hex" : "48ae05"
  },
  {
    "timesSeen" : [
      1740675968.6000001,
      1740758856.7,
      1740937570.6999998,
      1741215615.8999999,
      1741288127.9,
      1741305982.5,
      1741642527.3999999,
      1741719317.7,
      1742915460.7,
      1743276091.5,
      1743350961.4,
      1743910948.6,
      1743991730.1000001,
      1744082561.6,
      1744257271.8999999,
      1744480325.2,
      1744671393,
      1745026873.7,
      1745243697.5,
      1745625393.5,
      1745768677,
      1746203369.6999998,
      1746290190.1,
      1747243533.3,
      1747399353.5,
      1749070533.7,
      1753365961,
      1753395469.1000001,
      1753751691.3999999,
      1754012134.5,
      1754375249.1000001,
      1754867618,
      1754946348.2,
      1755101557.6000001,
      1755189190.3999999,
      1755271059.5,
      1755299883.5,
      1755361023.4,
      1755382756.6,
      1755474088.9,
      1755523638.4,
      1755609078.6000001,
      1755833215.3
    ],
    "flights" : {
      "UAL934  " : 1,
      "UAL965  " : 1,
      "UAL904  " : 1,
      "UAL110  " : 1,
      "UAL964  " : 1
    },
    "properties" : {
      "registered_owner_country_name" : "United States",
      "manufacturer" : "Boeing",
      "registration" : "N668UA",
      "registered_owner" : "United Airlines",
      "url_photo" : "https:\/\/airport-data.com\/images\/aircraft\/001\/269\/001269485.jpg",
      "registered_owner_country_iso_name" : "US",
      "registered_owner_operator_flag_code" : "UAL",
      "icao_type" : "B763",
      "type" : "767 322ER\/W"
    },
    "lastSeen" : 1755834222.4,
    "hex" : "a8d3b4"
  }
]